editor/README.md
editor/__init__.py
editor/__main__.py
editor/editor.py
editor/editor_widgets.py
editor/prototypes.py
editor/res/background.png
editor/res/cut.png
editor/res/delete.png
editor/res/drag.png
editor/res/minus.png
editor/res/paste.png
editor/res/plus.png
editor/res/preview.png
editor/res/resize.png
editor/res/style.css
editor/res/widget_Button.png
editor/res/widget_CheckBox.png
editor/res/widget_CheckBoxLabel.png
editor/res/widget_ColorPicker.png
editor/res/widget_Container.png
editor/res/widget_Date.png
editor/res/widget_DropDown.png
editor/res/widget_DropDownItem.png
editor/res/widget_FileFolderNavigator.png
editor/res/widget_FileUploader.png
editor/res/widget_GridBox.png
editor/res/widget_HBox.png
editor/res/widget_Image.png
editor/res/widget_Label.png
editor/res/widget_Link.png
editor/res/widget_ListItem.png
editor/res/widget_ListView.png
editor/res/widget_Progress.png
editor/res/widget_Slider.png
editor/res/widget_SpinBox.png
editor/res/widget_Svg.png
editor/res/widget_SvgCircle.png
editor/res/widget_SvgLine.png
editor/res/widget_SvgPath.png
editor/res/widget_SvgRectangle.png
editor/res/widget_SvgText.png
editor/res/widget_TabBox.png
editor/res/widget_TableWidget.png
editor/res/widget_TextInput.png
editor/res/widget_VBox.png
editor/res/widget_VideoPlayer.png
editor/res/tutorial_images/connect_button.png
editor/res/tutorial_images/drag_resize_button.png
editor/res/tutorial_images/drag_resize_container.png
editor/res/tutorial_images/drag_resize_label.png
editor/res/tutorial_images/edit_hello_message.png
editor/res/tutorial_images/hello.png
editor/res/tutorial_images/new_button.png
editor/res/tutorial_images/new_container.png
editor/res/tutorial_images/new_label.png
editor/res/tutorial_images/save_dialog.png
editor/res/tutorial_images/save_menu.png
editor/widgets/__init__.py
editor/widgets/toolbox_EPICS.py
editor/widgets/toolbox_opencv.py
editor/widgets/toolbox_scheduling.py
editor/widgets/toolbox_siemens.py
remi/__init__.py
remi/gui.py
remi/server.py
remi-2022.7.27.dist-info/LICENSE
remi-2022.7.27.dist-info/METADATA
remi-2022.7.27.dist-info/WHEEL
remi-2022.7.27.dist-info/top_level.txt
remi-2022.7.27.dist-info/RECORD
