Metadata-Version: 2.1
Name: remi
Version: 2022.7.27
Summary: Python REMote Interface library
Home-page: https://github.com/rawpython/remi
Download-URL: https://github.com/rawpython/remi/archive/master.zip
Author: Davide Rosa
Author-email: dddomodossola@gmail.com
License: Apache
Keywords: gui-library,remi,platform-independent,ui,gui
License-File: LICENSE
